project_structure_generator/__init__.py
project_structure_generator/generator.py
project_structure_builder-0.1.0.dist-info/METADATA
project_structure_builder-0.1.0.dist-info/WHEEL
project_structure_builder-0.1.0.dist-info/entry_points.txt
project_structure_builder-0.1.0.dist-info/top_level.txt
project_structure_builder-0.1.0.dist-info/RECORD
